LICENSE
README.md
setup.py
HiveNetPipeline/__init__.py
HiveNetPipeline/embed_predealer.py
HiveNetPipeline/embed_processer.py
HiveNetPipeline/embed_router.py
HiveNetPipeline/pipeline.py
HiveNetPipeline.egg-info/PKG-INFO
HiveNetPipeline.egg-info/SOURCES.txt
HiveNetPipeline.egg-info/dependency_links.txt
HiveNetPipeline.egg-info/not-zip-safe
HiveNetPipeline.egg-info/requires.txt
HiveNetPipeline.egg-info/top_level.txt