Metadata-Version: 2.1
Name: HiveNetPipeline
Version: 0.1.0
Summary: Realizes the management and implementation of simple pipeline mode processing flow.
Home-page: https://github.com/snakeclub/HiveNetAssemble/HiveNetPipeline
Author: 黎慧剑
Author-email: snakeclub@163.com
Maintainer: 黎慧剑
Maintainer-email: snakeclub@163.com
License: Mozilla Public License 2.0
Keywords: HiveNetAssemble HiveNetPipeline pipeline development python lib
Platform: all
Classifier: Operating System :: OS Independent
Classifier: License :: OSI Approved :: Mozilla Public License 2.0 (MPL 2.0)
Classifier: Programming Language :: Python :: 3.6
Classifier: Topic :: Software Development :: Libraries
License-File: LICENSE
